hoon.py
hoon-0.0.7.dist-info/WHEEL
hoon-0.0.7.dist-info/METADATA
hoon-0.0.7.dist-info/RECORD
