Metadata-Version: 2.1
Name: hoon
Version: 0.0.7
Summary: utility functions for DRY develpment
Author: Pedro Rodrigues
Author-email: medecau@gmail.com
Requires-Python: >=3.6,<4.0
Classifier: Programming Language :: Python :: 3
Classifier: Programming Language :: Python :: 3.6
Classifier: Programming Language :: Python :: 3.7
Classifier: Programming Language :: Python :: 3.8
Classifier: Programming Language :: Python :: 3.9
